f5_admin/__init__.py
f5_admin/f5_asm.py
f5_admin/f5_client.py
f5_admin/f5_data_group.py
f5_admin/f5_dep_tree.py
f5_admin/util.py
f5_admin/bin/asm-fetch
f5_admin/bin/asm-get
f5_admin/bin/asm-put
f5_admin/bin/dg-get
f5_admin/bin/dg-put
f5_admin/bin/f5-backup
f5_admin/bin/f5-delete
f5_admin/bin/f5-fetch
f5_admin/bin/f5-get
f5_admin/bin/f5-install-cert
f5_admin/bin/f5-put
f5_admin/bin/f5-resolve
f5_admin/bin/f5-run
f5_admin/bin/f5-runs
f5_admin/bin/f5-search
f5_admin/bin/f5-standby
f5_admin/bin/f5-sync
f5_admin/bin/oom-mon
f5_admin/bin/test.py
f5_admin/bin/test2.py
f5_admin/bin/test3.py
f5_admin-1.2.4.data/scripts/asm-fetch
f5_admin-1.2.4.data/scripts/asm-get
f5_admin-1.2.4.data/scripts/asm-put
f5_admin-1.2.4.data/scripts/dg-get
f5_admin-1.2.4.data/scripts/dg-put
f5_admin-1.2.4.data/scripts/f5-backup
f5_admin-1.2.4.data/scripts/f5-delete
f5_admin-1.2.4.data/scripts/f5-fetch
f5_admin-1.2.4.data/scripts/f5-get
f5_admin-1.2.4.data/scripts/f5-install-cert
f5_admin-1.2.4.data/scripts/f5-put
f5_admin-1.2.4.data/scripts/f5-resolve
f5_admin-1.2.4.data/scripts/f5-run
f5_admin-1.2.4.data/scripts/f5-runs
f5_admin-1.2.4.data/scripts/f5-search
f5_admin-1.2.4.data/scripts/f5-standby
f5_admin-1.2.4.data/scripts/f5-sync
f5_admin-1.2.4.data/scripts/oom-mon
f5_admin-1.2.4.dist-info/LICENSE.txt
f5_admin-1.2.4.dist-info/METADATA
f5_admin-1.2.4.dist-info/WHEEL
f5_admin-1.2.4.dist-info/top_level.txt
f5_admin-1.2.4.dist-info/RECORD
