Metadata-Version: 2.1
Name: f5-admin
Version: 1.2.4
Summary: Simple python package to manipulate F5 running configuration better and faster
Home-page: https://github.com/yangsec888/f5-admin
Author: Sam Li
Author-email: yangsec888@gmail.com
Keywords: DIY F5 Admin API / Utilities
Classifier: Development Status :: 5 - Production/Stable
Classifier: Programming Language :: Python :: 3
Classifier: License :: OSI Approved :: MIT License
Classifier: Operating System :: OS Independent
Classifier: Topic :: Software Development :: Build Tools
Requires-Python: >=3.6
License-File: LICENSE.txt
Requires-Dist: paramiko (>=2.4.1)
Requires-Dist: beautifulsoup4
Requires-Dist: xmltodict
